Metadata-Version: 2.1
Name: khansaar
Version: 1.0.0.0.0
Summary: this is the library to know salaar movie khannsaar relations and vote-count of the particular persons use names as "dhaara", "devaratha_raisaar", "shiva_mannar", "raja_mannar", "varadha_raj_mannar" baachi", "rudra", "radha_rama", "om", "narang", "vishnu", baarava"      and   use tribe names as shouryaanga, mannar, ghaniyar if you want get the vote count first specify tribe and second argument as a name of the person
Home-page: 
Author: jagilam kumar chandra
Author-email: jagilamkumar@gmail.com
